<?xml version="1.0" encoding="windows-1250"?>
<Experiment xmlns:xsi="http://www.w3.org/2001/XMLSchema-instance" xmlns:xsd="http://www.w3.org/2001/XMLSchema">
  <ExperimentStart>2018-04-15T22:57:04.5599427+02:00</ExperimentStart>
  <ExperimentEnd>2018-04-15T22:57:15.8602066+02:00</ExperimentEnd>
  <Tests>
    <Test>
      <Questions>
        <Question>
          <Text>Which of the two objects is more appealing to you?</Text>
          <ExperimentPart>0</ExperimentPart>
          <Options>
            <Option>Left</Option>
            <Option>Can't decide</Option>
            <Option>Right</Option>
          </Options>
          <Answer>0</Answer>
        </Question>
      </Questions>
      <ExperimentObjectName>box</ExperimentObjectName>
      <ObjectOneSettings>
        <EffectActive>true</EffectActive>
        <EffectName>Occlusion Map</EffectName>
        <PropertyName>_OcclusionMap</PropertyName>
        <PropertyType>texture</PropertyType>
        <EffectIntensity>1</EffectIntensity>
      </ObjectOneSettings>
      <ObjectTwoSettings>
        <EffectActive>false</EffectActive>
        <EffectName>Occlusion Map</EffectName>
        <PropertyName>_OcclusionMap</PropertyName>
        <PropertyType>texture</PropertyType>
        <EffectIntensity>0</EffectIntensity>
      </ObjectTwoSettings>
    </Test>
    <Test>
      <Questions>
        <Question>
          <Text>Which of the two objects is more appealing to you?</Text>
          <ExperimentPart>1</ExperimentPart>
          <Options>
            <Option>Left</Option>
            <Option>Can't decide</Option>
            <Option>Right</Option>
          </Options>
          <Answer>0</Answer>
        </Question>
      </Questions>
      <ExperimentObjectName>coffee_sack</ExperimentObjectName>
      <ObjectOneSettings>
        <EffectActive>true</EffectActive>
        <EffectName>Occlusion Map</EffectName>
        <PropertyName>_OcclusionMap</PropertyName>
        <PropertyType>texture</PropertyType>
        <EffectIntensity>1</EffectIntensity>
      </ObjectOneSettings>
      <ObjectTwoSettings>
        <EffectActive>false</EffectActive>
        <EffectName>Occlusion Map</EffectName>
        <PropertyName>_OcclusionMap</PropertyName>
        <PropertyType>texture</PropertyType>
        <EffectIntensity>0</EffectIntensity>
      </ObjectTwoSettings>
    </Test>
    <Test>
      <Questions>
        <Question>
          <Text>Which of the two objects is more appealing to you?</Text>
          <ExperimentPart>2</ExperimentPart>
          <Options>
            <Option>Left</Option>
            <Option>Can't decide</Option>
            <Option>Right</Option>
          </Options>
          <Answer>0</Answer>
        </Question>
      </Questions>
      <ExperimentObjectName>milk_churn</ExperimentObjectName>
      <ObjectOneSettings>
        <EffectActive>true</EffectActive>
        <EffectName>Normal Map</EffectName>
        <PropertyName>_BumpMap</PropertyName>
        <PropertyType>texture</PropertyType>
        <EffectIntensity>5</EffectIntensity>
      </ObjectOneSettings>
      <ObjectTwoSettings>
        <EffectActive>false</EffectActive>
        <EffectName>Normal Map</EffectName>
        <PropertyName>_BumpMap</PropertyName>
        <PropertyType>texture</PropertyType>
        <EffectIntensity>0</EffectIntensity>
      </ObjectTwoSettings>
    </Test>
  </Tests>
  <headsetInfo>OculusRiftCV1</headsetInfo>
</Experiment>